MANIFEST.in
README.md
setup.py
tissu/__init__.py
tissu/api.py
tissu/constants.py
tissu/importlib.py
tissu/tasks.py
tissu.egg-info/PKG-INFO
tissu.egg-info/SOURCES.txt
tissu.egg-info/dependency_links.txt
tissu.egg-info/requires.txt
tissu.egg-info/top_level.txt
tissu/conf/__init__.py
tissu/conf/global_settings.py