Metadata-Version: 1.1
Name: tissu
Version: 0.4-alpha
Summary: Tissu - Functions to handle settings with Fabric
Home-page: http://github.com/thierrystiegler/tissu
Author: Thierry Stiegler
Author-email: thierry.stiegler@gmail.com
License: License :: OSI Approved :: BSD License
Download-URL: https://github.com/thierrystiegler/tissu/tarball/0.4-alpha
Keywords: fabric,settings
Platform: UNKNOWN
Classifier: Programming Language :: Python
Classifier: Development Status :: 3 - Alpha
Classifier: Natural Language :: English
Classifier: Environment :: Web Environment
Classifier: Intended Audience :: Developers
Classifier: Operating System :: OS Independent
Classifier: Topic :: Utilities
